[
  {
    "Pregunta":
    {
      "tipo": "VerdaderoFalsoClasico",
      "nombre": "¿207 es un número primo?",
      "opcionCorrecta": false
    }
  },
  {
    "Pregunta":
    {
      "tipo": "VerdaderoFalsoPenalidad",
      "nombre": "¿Blanco es un color?",
      "opcionCorrecta": false
    }
  },
  {
    "Pregunta":
    {
      "tipo" : "MultipleChoiseParcial",
      "nombre":"¿Capital de Alemania?",
      "correctas": [
        "Berlin" ],
      "incorrectas": [
        "Paris",
        "Munich",
        "Amsterdam",
        "Roma"]
    }
  },
  {
    "Pregunta":
    {
      "tipo" : "MultipleChoiseParcial",
      "nombre":"¿Cap de Francia?",
      "correctas": [
        "Paris" ],
      "incorrectas": [
        "Berlin",
        "Barcelona",
        "Madrid",
        "Roma"]
    }
  },
  {
    "Pregunta": {
      "tipo": "MultipleChoiseParcial",
      "nombre": "Lagos Argentinos ",
      "correctas": [
        "Nahuel Huapi",
        "Viedma"
      ],
      "incorrectas": [
        "Gualeguay",
        "Esteros de Libera",
        "Uruguay"
      ]
    }
  },{
    "Pregunta": {
      "tipo": "OrderedChoise",
      "nombre": "Ordenar de Mayor a Menor",
      "correctas": [
        "20",
        "14",
        "12",
        "3"
      ]
    }
    },{
    "Pregunta": {
      "tipo": "GrupoChoice",
      "nombre": "Diferenciar entre ciudades de Europa y de Asia",
      "grupo1": [
        "Berlin" ],
      "grupo2": [
        "Paris",
        "Roma"]
    }
  }
]

